heregpt/__init__.py
heregpt/main.py
heregpt/models.py
heregpt/utils.py
heregpt-0.2.1.dist-info/LICENSE
heregpt-0.2.1.dist-info/METADATA
heregpt-0.2.1.dist-info/WHEEL
heregpt-0.2.1.dist-info/entry_points.txt
heregpt-0.2.1.dist-info/RECORD
