Metadata-Version: 2.1
Name: heregpt
Version: 0.2.1
Summary: Have ChatGPT right_here_ within your shell
Home-page: https://github.com/drorata/heregpt
License: MIT
Author: Dror Atariah
Author-email: drorata@gmail.com
Requires-Python: >=3.11,<4.0
Classifier: License :: OSI Approved :: MIT License
Classifier: Programming Language :: Python :: 3
Classifier: Programming Language :: Python :: 3.11
Requires-Dist: loguru (>=0.7.0,<0.8.0)
Requires-Dist: openai (>=0.27.8,<0.28.0)
Requires-Dist: pydantic (>=2.0.2,<3.0.0)
Requires-Dist: python-dotenv (>=1.0.0,<2.0.0)
Requires-Dist: typer[all] (>=0.9.0,<0.10.0)
Project-URL: Repository, https://github.com/drorata/heregpt
